{
  "id": "milesight-ms-c2964-fpd",
  "brand": "Milesight",
  "model": "MS-C2964-FPD",
  "type": "turret",
  "connectivity": [
    "ethernet"
  ],
  "resolution": {
    "megapixels": 2,
    "max_width": 1920,
    "max_height": 1080,
    "label": "1080p"
  },
  "sensor": "1/2.8\" Progressive Scan CMOS",
  "lens": {
    "count": 1,
    "focal_length_mm": "2.8",
    "varifocal": false
  },
  "field_of_view_deg": "109 horizontal",
  "night_vision": {
    "type": "ir",
    "range_m": 25
  },
  "power": {
    "method": "PoE (IEEE 802.3af) / DC 12V"
  },
  "storage": {
    "onboard": true,
    "max_microsd_gb": 256,
    "nvr_compatible": true,
    "cloud": false
  },
  "protocols": [
    "onvif",
    "rtsp"
  ],
  "ip_rating": "IP67",
  "audio": {
    "microphone": true,
    "speaker": false,
    "two_way": false
  },
  "features": [
    "smart IR",
    "H.265+ compression",
    "WDR 120dB",
    "3D DNR"
  ],
  "release_year": 2022,
  "sources": [
    "https://www.milesight.com/product/ms-c2964-fpd"
  ],
  "power_source": [
    "poe",
    "dc"
  ]
}
