{
  "id": "flir-elara-fb-324t",
  "brand": "FLIR",
  "model": "Elara FB-324T",
  "type": "dome",
  "connectivity": [
    "ethernet"
  ],
  "resolution": {
    "megapixels": 0.1,
    "max_width": 320,
    "max_height": 240,
    "label": "Thermal 320x240"
  },
  "sensor": "Uncooled VOx Microbolometer",
  "lens": {
    "count": 1,
    "focal_length_mm": "13",
    "varifocal": false
  },
  "field_of_view_deg": "24 horizontal",
  "night_vision": {
    "type": "ir",
    "range_m": 200
  },
  "power": {
    "method": "PoE (IEEE 802.3af) / DC 24V"
  },
  "storage": {
    "onboard": true,
    "max_microsd_gb": 128,
    "nvr_compatible": true,
    "cloud": false
  },
  "protocols": [
    "onvif",
    "rtsp"
  ],
  "ip_rating": "IP67",
  "audio": {
    "microphone": false,
    "speaker": false,
    "two_way": false
  },
  "features": [
    "thermal imaging",
    "perimeter analytics",
    "fixed dome housing",
    "IK10 vandal resistant"
  ],
  "release_year": 2019,
  "sources": [
    "https://www.flir.com/security/"
  ],
  "power_source": [
    "poe"
  ],
  "configs": {
    "frigate": {
      "detect": {
        "width": 640,
        "height": 480,
        "fps": 5
      },
      "rtsp_url_template": "rtsp://{user}:{pass}@{ip}:554/avc"
    },
    "home_assistant": {
      "integration": "onvif",
      "notes": "Use ONVIF integration."
    },
    "blue_iris": {
      "profile": "Generic/ONVIF",
      "notes": "Use Generic/ONVIF profile. RTSP path: /avc."
    }
  }
}
