{
  "id": "ubiquiti-unifi-g5-ptz",
  "brand": "Ubiquiti",
  "model": "UniFi G5 PTZ",
  "aliases": [
    "UVC-G5-PTZ",
    "UniFi 4K 22x Pan/Tilt/Zoom"
  ],
  "type": "ptz",
  "connectivity": [
    "poe",
    "ethernet"
  ],
  "release_year": 2023,
  "resolution": {
    "megapixels": 4,
    "max_width": 2688,
    "max_height": 1512,
    "label": "4MP QHD"
  },
  "sensor": "1/2.8\" CMOS",
  "lens": {
    "count": 1,
    "focal_length_mm": "4.3-94.6 (22x optical)",
    "aperture": "F1.6",
    "varifocal": true
  },
  "field_of_view_deg": "55-2.7 horizontal",
  "night_vision": {
    "type": "ir",
    "range_m": 50
  },
  "power": {
    "method": "PoE (802.3bt)"
  },
  "storage": {
    "onboard": false,
    "nvr_compatible": true,
    "cloud": false
  },
  "protocols": [
    "rtsp"
  ],
  "ip_rating": "IP66",
  "audio": {
    "microphone": true,
    "speaker": false,
    "two_way": false
  },
  "features": [
    "4MP 22x optical zoom PTZ",
    "360\u00b0 continuous pan",
    "UniFi Protect integration",
    "auto-tracking",
    "NDAA compliant",
    "IP66",
    "H.265 smart encoding",
    "popular prosumer/SMB PTZ"
  ],
  "msrp_usd": 499,
  "sources": [
    "https://store.ui.com/us/en/products/uvc-g5-ptz"
  ]
}