{
  "id": "provision-isr-di2-340ipe",
  "brand": "Provision-ISR",
  "model": "DI2-340IPE",
  "type": "dome",
  "connectivity": ["poe", "ethernet"],
  "resolution": { "megapixels": 2, "max_width": 1920, "max_height": 1080, "label": "1080p FHD" },
  "sensor": "1/2.8\" CMOS",
  "night_vision": { "type": "ir", "range_m": 25 },
  "power": { "method": "PoE (IEEE 802.3af) / DC 12V" },
  "storage": { "onboard": false, "nvr_compatible": true, "cloud": false },
  "protocols": ["onvif", "rtsp"],
  "ip_rating": "IP66",
  "audio": { "microphone": true, "speaker": false, "two_way": false },
  "features": [
    "person/vehicle detection",
    "vandal-resistant housing",
    "smart IR",
    "3D DNR",
    "H.265 compression"
  ],
  "sources": ["https://www.provision-isr.com/"]
}
