{
  "id": "hanwha-pnv-9300rv",
  "brand": "Hanwha",
  "model": "PNV-9300RV",
  "aliases": [
    "Wisenet P 4K Vandal Dome AI"
  ],
  "type": "dome",
  "connectivity": [
    "ethernet"
  ],
  "resolution": {
    "megapixels": 8,
    "max_width": 3840,
    "max_height": 2160,
    "label": "4K UHD"
  },
  "sensor": "1/1.8\" Progressive Scan CMOS",
  "lens": {
    "count": 1,
    "focal_length_mm": "3-8.5 (3x motorized)",
    "aperture": "F1.2",
    "varifocal": true
  },
  "field_of_view_deg": "108-38 horizontal",
  "night_vision": {
    "type": "ir",
    "range_m": 50
  },
  "power": {
    "method": "PoE (802.3af) / DC 12V"
  },
  "storage": {
    "onboard": true,
    "max_microsd_gb": 512,
    "nvr_compatible": true,
    "cloud": false
  },
  "protocols": [
    "onvif",
    "rtsp"
  ],
  "ip_rating": "IP66",
  "audio": {
    "microphone": false,
    "speaker": false,
    "two_way": false
  },
  "features": [
    "AI deep-learning face detection",
    "vehicle detection",
    "LPR support",
    "WiseStream III",
    "IVA Pro",
    "extreme WDR",
    "IK10",
    "NEMA 4X"
  ],
  "sources": [
    "https://hanwhavisionamerica.com/"
  ],
  "power_source": [
    "poe",
    "dc"
  ],
  "configs": {
    "frigate": {
      "detect": {
        "width": 1280,
        "height": 720,
        "fps": 5
      },
      "rtsp_url_template": "rtsp://{user}:{pass}@{ip}:554/profile1/media.smp",
      "best_substream": "rtsp://{user}:{pass}@{ip}:554/profile2/media.smp"
    },
    "home_assistant": {
      "integration": "onvif",
      "notes": "Use ONVIF integration. Default ONVIF port 80."
    }
  }
}
