{
  "id": "hikvision-ds-2cd2t86g2-4i",
  "brand": "Hikvision",
  "model": "DS-2CD2T86G2-4I",
  "aliases": [
    "AcuSense 8MP 80m IR Fixed Bullet EasyIP4"
  ],
  "type": "bullet",
  "connectivity": [
    "poe",
    "ethernet"
  ],
  "resolution": {
    "megapixels": 8,
    "max_width": 3840,
    "max_height": 2160,
    "label": "4K UHD"
  },
  "sensor": "1/2.8\" Progressive Scan CMOS",
  "lens": {
    "count": 1,
    "focal_length_mm": "2.8 / 4 (fixed)",
    "aperture": "F1.6",
    "varifocal": false
  },
  "field_of_view_deg": "102 horizontal (2.8mm)",
  "night_vision": {
    "type": "ir",
    "range_m": 80
  },
  "power": {
    "method": "PoE (802.3af) / DC 12V"
  },
  "storage": {
    "onboard": true,
    "max_microsd_gb": 256,
    "nvr_compatible": true,
    "cloud": false
  },
  "protocols": [
    "onvif",
    "rtsp"
  ],
  "ip_rating": "IP67",
  "audio": {
    "microphone": false,
    "speaker": false,
    "two_way": false
  },
  "features": [
    "AcuSense human/vehicle",
    "80m long-range IR",
    "120 dB WDR",
    "H.265+",
    "IK10"
  ],
  "sources": [
    "https://www.hikvision.com/en/products/"
  ]
}