{
  "id": "annke-cr400",
  "brand": "Annke",
  "model": "CR400",
  "aliases": [
    "4MP Color Night PoE Bullet"
  ],
  "type": "bullet",
  "connectivity": [
    "ethernet"
  ],
  "release_year": 2023,
  "resolution": {
    "megapixels": 4,
    "max_width": 2560,
    "max_height": 1440,
    "label": "4MP"
  },
  "lens": {
    "count": 1,
    "focal_length_mm": "2.8 (fixed)",
    "varifocal": false
  },
  "night_vision": {
    "type": "color",
    "range_m": 30
  },
  "power": {
    "method": "PoE (802.3af) / DC 12V"
  },
  "storage": {
    "onboard": false,
    "nvr_compatible": true,
    "cloud": false
  },
  "protocols": [
    "rtsp",
    "onvif"
  ],
  "ip_rating": "IP67",
  "audio": {
    "microphone": true,
    "speaker": false,
    "two_way": false
  },
  "features": [
    "4MP PoE bullet budget color night",
    "full-color night vision with warm LED",
    "built-in mic",
    "H.265+",
    "IP67",
    "ONVIF compatible"
  ],
  "msrp_usd": 39.99,
  "sources": [
    "https://www.annke.com/"
  ],
  "power_source": [
    "poe",
    "dc"
  ],
  "configs": {
    "frigate": {
      "detect": {
        "width": 1280,
        "height": 720,
        "fps": 5
      },
      "rtsp_url_template": "rtsp://{user}:{pass}@{ip}:554/Streaming/Channels/101",
      "best_substream": "rtsp://{user}:{pass}@{ip}:554/Streaming/Channels/102"
    },
    "home_assistant": {
      "integration": "onvif",
      "notes": "Uses Hikvision protocol. ONVIF integration works."
    },
    "blue_iris": {
      "profile": "Hikvision",
      "notes": "Select 'Hikvision' profile. Most Annke cameras use Hikvision protocol."
    }
  }
}
