{
  "id": "amcrest-ad410-doorbell",
  "brand": "Amcrest",
  "model": "AD410 2K Video Doorbell",
  "aliases": [
    "Amcrest Smart Home 2K WiFi Video Doorbell AD410"
  ],
  "type": "doorbell",
  "connectivity": [
    "wifi"
  ],
  "release_year": 2022,
  "resolution": {
    "megapixels": 4,
    "max_width": 2560,
    "max_height": 1440,
    "label": "2K QHD"
  },
  "lens": {
    "count": 1,
    "focal_length_mm": "Fixed",
    "aperture": "F2.0",
    "varifocal": false
  },
  "field_of_view_deg": "163 diagonal (head-to-toe)",
  "night_vision": {
    "type": "color",
    "range_m": 5
  },
  "power": {
    "method": "Hardwired (16-24V AC) / battery"
  },
  "storage": {
    "onboard": false,
    "nvr_compatible": false,
    "cloud": true
  },
  "protocols": [
    "onvif",
    "rtsp",
    "http"
  ],
  "ip_rating": "IP65",
  "audio": {
    "microphone": true,
    "speaker": true,
    "two_way": true
  },
  "features": [
    "2K QHD video doorbell",
    "color night vision",
    "head-to-toe view",
    "person/package detection",
    "two-way audio",
    "Alexa compatible",
    "Blue Iris compatible",
    "IP65",
    "no subscription required"
  ],
  "msrp_usd": 79,
  "sources": [
    "https://amcrest.com/products/video-doorbells/ad410"
  ],
  "power_source": [
    "battery",
    "ac-mains"
  ],
  "configs": {
    "frigate": {
      "detect": {
        "width": 720,
        "height": 960,
        "fps": 5
      },
      "rtsp_url_template": "rtsp://{user}:{pass}@{ip}:554/cam/realmonitor?channel=1&subtype=0",
      "best_substream": "rtsp://{user}:{pass}@{ip}:554/cam/realmonitor?channel=1&subtype=1",
      "notes": "Uses Dahua protocol (Amcrest standard). Portrait 3:4 aspect ratio — set detect to 720x960. Community favorite for local-only doorbell with Frigate. Button press exposed as Dahua event (AccessControl/CallNoAnswered). For two-way audio use go2rtc with Dahua back-channel."
    },
    "home_assistant": {
      "integration": "amcrest",
      "notes": "Native Amcrest integration. Doorbell button press exposed as 'doorbell' event entity. Two-way audio supported. Also works with ONVIF integration."
    },
    "blue_iris": {
      "profile": "Dahua",
      "notes": "Select 'Dahua' profile. Portrait 3:4 aspect ratio. Doorbell press triggers alert."
    }
  }
}
